setup.py
isfoPy/__init__.py
isfoPy.egg-info/PKG-INFO
isfoPy.egg-info/SOURCES.txt
isfoPy.egg-info/dependency_links.txt
isfoPy.egg-info/top_level.txt